<T3DataStructure>
    <ROOT>
        <sheetTitle>LLL:EXT:codehighlight/Resources/Private/Language/ContentElement.xlf:styles</sheetTitle>
        <type>array</type>
        <el>
            <inlineColour>
                <label>LLL:EXT:codehighlight/Resources/Private/Language/ContentElement.xlf:inlineColour</label>
                <description>LLL:EXT:codehighlight/Resources/Private/Language/ContentElement.xlf:inlineColour.description</description>
                <config>
                    <type>check</type>
                    <renderType>checkboxToggle</renderType>
                    <items>
                        <numIndex index="0" type="array">
                            <numIndex index="0"/>
                            <numIndex index="1"/>
                        </numIndex>
                    </items>
                </config>
            </inlineColour>
        </el>
    </ROOT>
</T3DataStructure>
